fgcp/__init__.py
fgcp/client.py
fgcp/command.py
fgcp/connection.py
fgcp/design.py
fgcp/dummy.py
fgcp/resource.py
fgcp/server.py
fgcp/libcloud/__init__.py
fgcp/libcloud/backup.py
fgcp/libcloud/common.py
fgcp/libcloud/compute.py
fgcp/libcloud/container.py
fgcp/libcloud/dns.py
fgcp/libcloud/loadbalancer.py
fgcp/libcloud/storage.py
fgcp_client_api-1.5.0.dist-info/METADATA
fgcp_client_api-1.5.0.dist-info/RECORD
fgcp_client_api-1.5.0.dist-info/WHEEL
fgcp_client_api-1.5.0.dist-info/entry_points.txt
fgcp_client_api-1.5.0.dist-info/top_level.txt
