Metadata-Version: 2.1
Name: fgcp-client-api
Version: 1.5.0
Summary: Client API Library for the Fujitsu Global Cloud Platform (FGCP)
Home-page: https://github.com/mikespub/fgcp-client-api
Author: mikespub
Author-email: fgcp@mikespub.net
License: Apache License 2.0
Platform: UNKNOWN
Classifier: Topic :: Software Development :: Libraries :: Python Modules
Classifier: Environment :: Console
Classifier: Environment :: Web Environment
Classifier: Development Status :: 4 - Beta
Classifier: Intended Audience :: System Administrators
Classifier: Intended Audience :: Developers
Classifier: License :: OSI Approved :: Apache Software License
Classifier: Operating System :: OS Independent
Classifier: Programming Language :: Python :: 2.7
Classifier: Programming Language :: Python :: 3.6
